{"_path":"/api/ox","_dir":"api","_draft":false,"_partial":false,"_locale":"","title":"Overextended","description":"Their projects will always remain free and open-source, with their core developers working voluntarily. If you love what they do and want to help them continue, why not show your appreciation with a donation?","body":{"type":"root","children":[{"type":"element","tag":"h1","props":{"id":"overextended"},"children":[{"type":"text","value":"Overextended"}]},{"type":"element","tag":"p","props":{},"children":[{"type":"text","value":"Their projects will always remain free and open-source, with their core developers working voluntarily. If you love what they do and want to help them continue, why not show your appreciation with a donation?"}]},{"type":"element","tag":"h4","props":{"id":"resources-used"},"children":[{"type":"text","value":"Resources Used:"}]},{"type":"element","tag":"list","props":{"type":"success"},"children":[{"type":"element","tag":"ul","props":{},"children":[{"type":"element","tag":"li","props":{},"children":[{"type":"element","tag":"a","props":{"href":"https://github.com/overextended/ox_core","rel":["nofollow"]},"children":[{"type":"text","value":"ox_core"}]}]},{"type":"element","tag":"li","props":{},"children":[{"type":"element","tag":"a","props":{"href":"https://github.com/overextended/ox_lib","rel":["nofollow"]},"children":[{"type":"text","value":"ox_lib"}]}]},{"type":"element","tag":"li","props":{},"children":[{"type":"element","tag":"a","props":{"href":"https://github.com/overextended/ox_inventory","rel":["nofollow"]},"children":[{"type":"text","value":"ox_inventory"}]}]},{"type":"element","tag":"li","props":{},"children":[{"type":"element","tag":"a","props":{"href":"https://github.com/overextended/ox_appearance","rel":["nofollow"]},"children":[{"type":"text","value":"ox_appearance"}]}]},{"type":"element","tag":"li","props":{},"children":[{"type":"element","tag":"a","props":{"href":"https://github.com/overextended/oxmysql","rel":["nofollow"]},"children":[{"type":"text","value":"oxmysql"}]}]}]}]},{"type":"element","tag":"h4","props":{"id":"socials"},"children":[{"type":"text","value":"Socials:"}]},{"type":"element","tag":"list","props":{"type":"success"},"children":[{"type":"element","tag":"ul","props":{},"children":[{"type":"element","tag":"li","props":{},"children":[{"type":"element","tag":"a","props":{"href":"https://discord.overextended.dev/","rel":["nofollow"]},"children":[{"type":"text","value":"Discord"}]},{"type":"text","value":" ... "},{"type":"element","tag":"icon","props":{"name":"simple-icons:discord"},"children":[]}]},{"type":"element","tag":"li","props":{},"children":[{"type":"element","tag":"a","props":{"href":"https://github.overextended.dev/","rel":["nofollow"]},"children":[{"type":"text","value":"Github"}]},{"type":"text","value":" ... "},{"type":"element","tag":"icon","props":{"name":"simple-icons:github"},"children":[]}]},{"type":"element","tag":"li","props":{},"children":[{"type":"element","tag":"a","props":{"href":"https://overextended.dev/","rel":["nofollow"]},"children":[{"type":"text","value":"Documentation"}]},{"type":"text","value":" ... "},{"type":"element","tag":"icon","props":{"name":"mdi:clipboard-text-multiple"},"children":[]}]}]}]}],"toc":{"title":"","searchDepth":2,"depth":2,"links":[]}},"_type":"markdown","_id":"content:2.api:4.ox.md","_source":"content","_file":"2.api/4.ox.md","_extension":"md"}